lilt/__init__.py
lilt/api_client.py
lilt/configuration.py
lilt/exceptions.py
lilt/rest.py
lilt/api/__init__.py
lilt/api/comments_api.py
lilt/api/connectors_api.py
lilt/api/converter_config_api.py
lilt/api/documents_api.py
lilt/api/files_api.py
lilt/api/jobs_api.py
lilt/api/languages_api.py
lilt/api/lexicon_api.py
lilt/api/memories_api.py
lilt/api/projects_api.py
lilt/api/qa_api.py
lilt/api/root_api.py
lilt/api/segments_api.py
lilt/api/settings_api.py
lilt/api/translate_api.py
lilt/models/__init__.py
lilt/models/add_file_label_request.py
lilt/models/annotation.py
lilt/models/api_root.py
lilt/models/comment.py
lilt/models/comment_body.py
lilt/models/comment_delete_response.py
lilt/models/connector.py
lilt/models/connector1.py
lilt/models/connector_arguments.py
lilt/models/connector_delete_response.py
lilt/models/connector_job.py
lilt/models/converter_config_update_response.py
lilt/models/create_converter_config_parameters.py
lilt/models/document_assignment_parameters.py
lilt/models/document_assignment_response.py
lilt/models/document_comments.py
lilt/models/document_delete_response.py
lilt/models/document_done_update_parameters.py
lilt/models/document_done_update_parameters1.py
lilt/models/document_done_update_parameters2.py
lilt/models/document_parameters.py
lilt/models/document_pretranslate_parameters.py
lilt/models/document_pretranslate_response.py
lilt/models/document_pretranslating.py
lilt/models/document_pretranslating_status.py
lilt/models/document_quote.py
lilt/models/document_update_parameters.py
lilt/models/document_with_segments.py
lilt/models/document_without_segments.py
lilt/models/document_without_segments_status.py
lilt/models/edit_filter_mapping_parameters.py
lilt/models/error.py
lilt/models/error2.py
lilt/models/file.py
lilt/models/file_delete_response.py
lilt/models/file_response.py
lilt/models/inline_response200.py
lilt/models/inline_response201.py
lilt/models/job.py
lilt/models/job_create_parameters.py
lilt/models/job_delete_response.py
lilt-0.6.7.dist-info/METADATA
lilt-0.6.7.dist-info/WHEEL
lilt-0.6.7.dist-info/top_level.txt
lilt-0.6.7.dist-info/RECORD
