Metadata-Version: 2.1
Name: lilt
Version: 0.6.7
Summary: Lilt REST API
Home-page: https://github.com/lilt/lilt-python
Author: Lilt REST API Support
Author-email: support@lilt.com
License: UNKNOWN
Keywords: OpenAPI,OpenAPI-Generator,Lilt REST API
Platform: UNKNOWN
Requires-Dist: urllib3 (>=1.15)
Requires-Dist: six (>=1.10)
Requires-Dist: certifi
Requires-Dist: python-dateutil
